jupyterlab_night/__init__.py
jupyterlab_night/_version.py
jupyterlab_night-0.5.1.data/data/share/jupyter/labextensions/jupyterlab-night/package.json
jupyterlab_night-0.5.1.data/data/share/jupyter/labextensions/jupyterlab-night/static/509.58a4a2e225d75bbc7c3c.js
jupyterlab_night-0.5.1.data/data/share/jupyter/labextensions/jupyterlab-night/static/remoteEntry.2105cdd7da221c68dcd3.js
jupyterlab_night-0.5.1.data/data/share/jupyter/labextensions/jupyterlab-night/static/style.js
jupyterlab_night-0.5.1.data/data/share/jupyter/labextensions/jupyterlab-night/static/third-party-licenses.json
jupyterlab_night-0.5.1.data/data/share/jupyter/labextensions/jupyterlab-night/themes/jupyterlab-night/index.css
jupyterlab_night-0.5.1.data/data/share/jupyter/labextensions/jupyterlab-night/themes/jupyterlab-night/index.js
jupyterlab_night-0.5.1.data/data/share/jupyter/labextensions/jupyterlab-night/install.json
jupyterlab_night-0.5.1.dist-info/METADATA
jupyterlab_night-0.5.1.dist-info/WHEEL
jupyterlab_night-0.5.1.dist-info/licenses/LICENSE
jupyterlab_night-0.5.1.dist-info/RECORD
