Metadata-Version: 2.3
Name: jupyterlab_night
Version: 0.5.1
Summary: Dark theme for JupyterLab
Project-URL: Homepage, https://github.com/jupyterlab-contrib/jupyterlab-night
Project-URL: Bug Tracker, https://github.com/jupyterlab-contrib/jupyterlab-night/issues
Project-URL: Repository, https://github.com/jupyterlab-contrib/jupyterlab-night.git
Author-email: Martin Renou <martin.renou@gmail.com>
License: BSD 3-Clause License
Keywords: jupyter,jupyterlab,jupyterlab-extension
Classifier: Framework :: Jupyter
Classifier: Framework :: Jupyter :: JupyterLab
Classifier: Framework :: Jupyter :: JupyterLab :: 4
Classifier: Framework :: Jupyter :: JupyterLab :: Extensions
Classifier: Framework :: Jupyter :: JupyterLab :: Extensions :: Prebuilt
Classifier: Framework :: Jupyter :: JupyterLab :: Extensions :: Themes
Classifier: License :: OSI Approved :: BSD License
Classifier: Programming Language :: Python
Classifier: Programming Language :: Python :: 3
Classifier: Programming Language :: Python :: 3.8
Classifier: Programming Language :: Python :: 3.9
Classifier: Programming Language :: Python :: 3.10
Classifier: Programming Language :: Python :: 3.11
Classifier: Programming Language :: Python :: 3.12
Requires-Python: >=3.8
